phowr_router/__init__.py
phowr_router/core/__init__.py
phowr_router/core/middleware.py
phowr_router/core/router.py
phowr_router-1.0.3.dist-info/LICENSE.txt
phowr_router-1.0.3.dist-info/METADATA
phowr_router-1.0.3.dist-info/WHEEL
phowr_router-1.0.3.dist-info/top_level.txt
phowr_router-1.0.3.dist-info/RECORD
