Metadata-Version: 2.1
Name: phowr-router
Version: 1.0.3
Summary: Phowr Router
Home-page: https://github.com/hdsme/phowr-router
Download-URL: https://github.com/hdsme/phowr-router/tarball/1.0.3
Author: Hao Hoang
Author-email: haohoangofficial@gmail.com
License: LICENSE.txt
License-File: LICENSE.txt
Requires-Dist: fastap
